pyfiberc/__init__.py
pyfiberc/materials.py
pyfiberc/tools/__init__.py
pyfiberc/tools/models.py
pyfiberc-0.0.7.dist-info/METADATA
pyfiberc-0.0.7.dist-info/WHEEL
pyfiberc-0.0.7.dist-info/entry_points.txt
pyfiberc-0.0.7.dist-info/RECORD
