Metadata-Version: 2.4
Name: pyfiberc
Version: 0.0.7
Summary: fibred rc sections tool
Author-email: Marco Melcarne <mmelcarne@systra.com>, Luigi Luis Paone <ppc.luigi.paone@gmail.com>
Requires-Python: <3.13,>=3.9
Requires-Dist: mypy>=1.11
Requires-Dist: pycivil>=0.2.11
Requires-Dist: pydantic>=2.12.3
